{"room":{"name":"asdf","width":"25","height":25,"map":[[{"type":"grass","imageClass":"i-terrain-grassv1"},{"type":"grass","imageClass":"i-terrain-grassv1"},{"type":"grass","imageClass":"i-terrain-grassv1"},{"type":"grass","imageClass":"i-terrain-grassv1"},{"type":"grass","imageClass":"i-terrain-grassv1"},{"type":"grass","imageClass":"i-terrain-grassv1"},{"type":"grass","imageClass":"i-terrain-grassv1"},{"type":"grass","imageClass":"i-terrain-grassv1"},{"type":"grass","imageClass":"i-terrain-grassv1"},{"type":"grass","imageClass":"i-terrain-grassv1"},{"type":"grass","imageClass":"i-terrain-grassv1"},{"type":"grass","imageClass":"i-terrain-grassv1"},{"type":"grass","imageClass":"i-terrain-grassv1"},{"type":"grass","imageClass":"i-terrain-grassv1"},{"type":"grass","imageClass":"i-terrain-grassv1"},{"type":"grass","imageClass":"i-terrain-grassv1"},{"type":"grass","imageClass":"i-terrain-grassv1"},{"type":"grass","imageClass":"i-terrain-grassv1"},{"type":"grass","imageClass":"i-terrain-grassv1"},{"type":"grass","imageClass":"i-terrain-grassv1"},{"type":"grass","imageClass":"i-terrain-grassv1"},{"type":"grass","imageClass":"i-terrain-grassv1"},{"type":"grass","imageClass":"i-terrain-grassv1"},{"type":"grass","imageClass":"i-terrain-grassv1"},{"type":"grass","imageClass":"i-terrain-grassv1"}],[{"type":"grass","imageClass":"i-terrain-grassv1"},{"type":"grass","imageClass":"i-terrain-grassv1"},{"type":"grass","imageClass":"i-terrain-grassv1"},{"type":"grass","imageClass":"i-terrain-grassv1"},{"type":"grass","imageClass":"i-terrain-grassv1"},{"type":"grass","imageClass":"i-terrain-grassv1"},{"type":"grass","imageClass":"i-terrain-grassv1"},{"type":"grass","imageClass":"i-terrain-grassv1"},{"type":"grass","imageClass":"i-terrain-grassv1"},{"type":"grass","imageClass":"i-terrain-grassv1"},{"type":"grass","imageClass":"i-terrain-grassv1"},{"type":"road","imageClass":"i-terrain-roadev1"},{"type":"road","imageClass":"i-terrain-roadwv3"},{"type":"grass","imageClass":"i-terrain-grassv1"},{"type":"grass","imageClass":"i-terrain-grassv1"},{"type":"grass","imageClass":"i-terrain-grassv1"},{"type":"grass","imageClass":"i-terrain-grassv1"},{"type":"grass","imageClass":"i-terrain-grassv1"},{"type":"grass","imageClass":"i-terrain-grassv1"},{"type":"grass","imageClass":"i-terrain-grassv1"},{"type":"grass","imageClass":"i-terrain-grassv1"},{"type":"grass","imageClass":"i-terrain-grassv1"},{"type":"grass","imageClass":"i-terrain-grassv1"},{"type":"grass","imageClass":"i-terrain-grassv1"},{"type":"grass","imageClass":"i-terrain-grassv1"}],[{"type":"grass","imageClass":"i-terrain-grassv1"},{"type":"grass","imageClass":"i-terrain-grassv1"},{"type":"grass","imageClass":"i-terrain-grassv1"},{"type":"grass","imageClass":"i-terrain-grassv1"},{"type":"grass","imageClass":"i-terrain-grassv1"},{"type":"grass","imageClass":"i-terrain-grassv1"},{"type":"grass","imageClass":"i-terrain-grassv1"},{"type":"grass","imageClass":"i-terrain-grassv1"},{"type":"grass","imageClass":"i-terrain-grassv1"},{"type":"grass","imageClass":"i-terrain-grassv1"},{"type":"road","imageClass":"i-terrain-roadsev3"},{"type":"road","imageClass":"i-terrain-roadnwv4"},{"type":"road","imageClass":"i-terrain-roadnev1"},{"type":"road","imageClass":"i-terrain-roadswv4"},{"type":"grass","imageClass":"i-terrain-grassv1"},{"type":"grass","imageClass":"i-terrain-grassv1"},{"type":"grass","imageClass":"i-terrain-grassv1"},{"type":"grass","imageClass":"i-terrain-grassv1"},{"type":"grass","imageClass":"i-terrain-grassv1"},{"type":"grass","imageClass":"i-terrain-grassv1"},{"type":"grass","imageClass":"i-terrain-grassv1"},{"type":"grass","imageClass":"i-terrain-grassv1"},{"type":"grass","imageClass":"i-terrain-grassv1"},{"type":"grass","imageClass":"i-terrain-grassv1"},{"type":"grass","imageClass":"i-terrain-grassv1"}],[{"type":"grass","imageClass":"i-terrain-grassv1"},{"type":"grass","imageClass":"i-terrain-grassv1"},{"type":"grass","imageClass":"i-terrain-grassv1"},{"type":"grass","imageClass":"i-terrain-grassv1"},{"type":"grass","imageClass":"i-terrain-grassv1"},{"type":"grass","imageClass":"i-terrain-grassv1"},{"type":"grass","imageClass":"i-terrain-grassv1"},{"type":"grass","imageClass":"i-terrain-grassv1"},{"type":"grass","imageClass":"i-terrain-grassv1"},{"type":"grass","imageClass":"i-terrain-grassv1"},{"type":"road","imageClass":"i-terrain-roadnsv4"},{"type":"grass","imageClass":"i-terrain-grassv1"},{"type":"grass","imageClass":"i-terrain-grassv1"},{"type":"road","imageClass":"i-terrain-roadnev4"},{"type":"road","imageClass":"i-terrain-roadswv4"},{"type":"grass","imageClass":"i-terrain-grassv1"},{"type":"grass","imageClass":"i-terrain-grassv1"},{"type":"grass","imageClass":"i-terrain-grassv1"},{"type":"grass","imageClass":"i-terrain-grassv1"},{"type":"grass","imageClass":"i-terrain-grassv1"},{"type":"grass","imageClass":"i-terrain-grassv1"},{"type":"grass","imageClass":"i-terrain-grassv1"},{"type":"grass","imageClass":"i-terrain-grassv1"},{"type":"grass","imageClass":"i-terrain-grassv1"},{"type":"grass","imageClass":"i-terrain-grassv1"}],[{"type":"grass","imageClass":"i-terrain-grassv1"},{"type":"grass","imageClass":"i-terrain-grassv1"},{"type":"grass","imageClass":"i-terrain-grassv1"},{"type":"grass","imageClass":"i-terrain-grassv1"},{"type":"grass","imageClass":"i-terrain-grassv1"},{"type":"grass","imageClass":"i-terrain-grassv1"},{"type":"grass","imageClass":"i-terrain-grassv1"},{"type":"grass","imageClass":"i-terrain-grassv1"},{"type":"grass","imageClass":"i-terrain-grassv1"},{"type":"grass","imageClass":"i-terrain-grassv1"},{"type":"grass","imageClass":"i-terrain-grassv1"},{"type":"grass","imageClass":"i-terrain-grassv1"},{"type":"grass","imageClass":"i-terrain-grassv1"},{"type":"grass","imageClass":"i-terrain-grassv1"},{"type":"road","imageClass":"i-terrain-roadnsv3"},{"type":"grass","imageClass":"i-terrain-grassv1"},{"type":"grass","imageClass":"i-terrain-grassv1"},{"type":"grass","imageClass":"i-terrain-grassv1"},{"type":"grass","imageClass":"i-terrain-grassv1"},{"type":"grass","imageClass":"i-terrain-grassv1"},{"type":"grass","imageClass":"i-terrain-grassv1"},{"type":"grass","imageClass":"i-terrain-grassv1"},{"type":"grass","imageClass":"i-terrain-grassv1"},{"type":"grass","imageClass":"i-terrain-grassv1"},{"type":"grass","imageClass":"i-terrain-grassv1"}],[{"type":"grass","imageClass":"i-terrain-grassv1"},{"type":"grass","imageClass":"i-terrain-grassv1"},{"type":"grass","imageClass":"i-terrain-grassv1"},{"type":"grass","imageClass":"i-terrain-grassv1"},{"type":"grass","imageClass":"i-terrain-grassv1"},{"type":"grass","imageClass":"i-terrain-grassv1"},{"type":"grass","imageClass":"i-terrain-grassv1"},{"type":"grass","imageClass":"i-terrain-grassv1"},{"type":"grass","imageClass":"i-terrain-grassv1"},{"type":"grass","imageClass":"i-terrain-grassv1"},{"type":"grass","imageClass":"i-terrain-grassv1"},{"type":"grass","imageClass":"i-terrain-grassv1"},{"type":"grass","imageClass":"i-terrain-grassv1"},{"type":"grass","imageClass":"i-terrain-grassv1"},{"type":"road","imageClass":"i-terrain-roadnsv2"},{"type":"grass","imageClass":"i-terrain-grassv1"},{"type":"grass","imageClass":"i-terrain-grassv1"},{"type":"grass","imageClass":"i-terrain-grassv1"},{"type":"grass","imageClass":"i-terrain-grassv1"},{"type":"grass","imageClass":"i-terrain-grassv1"},{"type":"grass","imageClass":"i-terrain-grassv1"},{"type":"grass","imageClass":"i-terrain-grassv1"},{"type":"grass","imageClass":"i-terrain-grassv1"},{"type":"grass","imageClass":"i-terrain-grassv1"},{"type":"grass","imageClass":"i-terrain-grassv1"}],[{"type":"grass","imageClass":"i-terrain-grassv1"},{"type":"grass","imageClass":"i-terrain-grassv1"},{"type":"grass","imageClass":"i-terrain-grassv1"},{"type":"grass","imageClass":"i-terrain-grassv1"},{"type":"grass","imageClass":"i-terrain-grassv1"},{"type":"grass","imageClass":"i-terrain-grassv1"},{"type":"grass","imageClass":"i-terrain-grassv1"},{"type":"grass","imageClass":"i-terrain-grassv1"},{"type":"grass","imageClass":"i-terrain-grassv1"},{"type":"grass","imageClass":"i-terrain-grassv1"},{"type":"grass","imageClass":"i-terrain-grassv1"},{"type":"grass","imageClass":"i-terrain-grassv1"},{"type":"grass","imageClass":"i-terrain-grassv1"},{"type":"grass","imageClass":"i-terrain-grassv1"},{"type":"road","imageClass":"i-terrain-roadnsv3"},{"type":"grass","imageClass":"i-terrain-grassv1"},{"type":"grass","imageClass":"i-terrain-grassv1"},{"type":"grass","imageClass":"i-terrain-grassv1"},{"type":"grass","imageClass":"i-terrain-grassv1"},{"type":"grass","imageClass":"i-terrain-grassv1"},{"type":"grass","imageClass":"i-terrain-grassv1"},{"type":"grass","imageClass":"i-terrain-grassv1"},{"type":"grass","imageClass":"i-terrain-grassv1"},{"type":"grass","imageClass":"i-terrain-grassv1"},{"type":"grass","imageClass":"i-terrain-grassv1"}],[{"type":"grass","imageClass":"i-terrain-grassv1"},{"type":"grass","imageClass":"i-terrain-grassv1"},{"type":"grass","imageClass":"i-terrain-grassv1"},{"type":"grass","imageClass":"i-terrain-grassv1"},{"type":"grass","imageClass":"i-terrain-grassv1"},{"type":"grass","imageClass":"i-terrain-grassv1"},{"type":"grass","imageClass":"i-terrain-grassv1"},{"type":"grass","imageClass":"i-terrain-grassv1"},{"type":"grass","imageClass":"i-terrain-grassv1"},{"type":"grass","imageClass":"i-terrain-grassv1"},{"type":"grass","imageClass":"i-terrain-grassv1"},{"type":"grass","imageClass":"i-terrain-grassv1"},{"type":"grass","imageClass":"i-terrain-grassv1"},{"type":"grass","imageClass":"i-terrain-grassv1"},{"type":"road","imageClass":"i-terrain-roadnsv2"},{"type":"grass","imageClass":"i-terrain-grassv1"},{"type":"grass","imageClass":"i-terrain-grassv1"},{"type":"grass","imageClass":"i-terrain-grassv1"},{"type":"grass","imageClass":"i-terrain-grassv1"},{"type":"grass","imageClass":"i-terrain-grassv1"},{"type":"grass","imageClass":"i-terrain-grassv1"},{"type":"grass","imageClass":"i-terrain-grassv1"},{"type":"grass","imageClass":"i-terrain-grassv1"},{"type":"grass","imageClass":"i-terrain-grassv1"},{"type":"grass","imageClass":"i-terrain-grassv1"}],[{"type":"grass","imageClass":"i-terrain-grassv1"},{"type":"grass","imageClass":"i-terrain-grassv1"},{"type":"grass","imageClass":"i-terrain-grassv1"},{"type":"grass","imageClass":"i-terrain-grassv1"},{"type":"grass","imageClass":"i-terrain-grassv1"},{"type":"grass","imageClass":"i-terrain-grassv1"},{"type":"grass","imageClass":"i-terrain-grassv1"},{"type":"grass","imageClass":"i-terrain-grassv1"},{"type":"grass","imageClass":"i-terrain-grassv1"},{"type":"grass","imageClass":"i-terrain-grassv1"},{"type":"grass","imageClass":"i-terrain-grassv1"},{"type":"grass","imageClass":"i-terrain-grassv1"},{"type":"grass","imageClass":"i-terrain-grassv1"},{"type":"grass","imageClass":"i-terrain-grassv1"},{"type":"road","imageClass":"i-terrain-roadnev1"},{"type":"road","imageClass":"i-terrain-roadwev1"},{"type":"road","imageClass":"i-terrain-roadwev2"},{"type":"road","imageClass":"i-terrain-roadwev2"},{"type":"road","imageClass":"i-terrain-roadwev1"},{"type":"road","imageClass":"i-terrain-roadwev2"},{"type":"grass","imageClass":"i-terrain-grassv1"},{"type":"grass","imageClass":"i-terrain-grassv1"},{"type":"grass","imageClass":"i-terrain-grassv1"},{"type":"grass","imageClass":"i-terrain-grassv1"},{"type":"grass","imageClass":"i-terrain-grassv1"}],[{"type":"grass","imageClass":"i-terrain-grassv1"},{"type":"grass","imageClass":"i-terrain-grassv1"},{"type":"grass","imageClass":"i-terrain-grassv1"},{"type":"grass","imageClass":"i-terrain-grassv1"},{"type":"grass","imageClass":"i-terrain-grassv1"},{"type":"grass","imageClass":"i-terrain-grassv1"},{"type":"grass","imageClass":"i-terrain-grassv1"},{"type":"grass","imageClass":"i-terrain-grassv1"},{"type":"grass","imageClass":"i-terrain-grassv1"},{"type":"grass","imageClass":"i-terrain-grassv1"},{"type":"grass","imageClass":"i-terrain-grassv1"},{"type":"grass","imageClass":"i-terrain-grassv1"},{"type":"grass","imageClass":"i-terrain-grassv1"},{"type":"grass","imageClass":"i-terrain-grassv1"},{"type":"grass","imageClass":"i-terrain-grassv1"},{"type":"grass","imageClass":"i-terrain-grassv1"},{"type":"grass","imageClass":"i-terrain-grassv1"},{"type":"grass","imageClass":"i-terrain-grassv1"},{"type":"grass","imageClass":"i-terrain-grassv1"},{"type":"grass","imageClass":"i-terrain-grassv1"},{"type":"grass","imageClass":"i-terrain-grassv1"},{"type":"grass","imageClass":"i-terrain-grassv1"},{"type":"grass","imageClass":"i-terrain-grassv1"},{"type":"grass","imageClass":"i-terrain-grassv1"},{"type":"grass","imageClass":"i-terrain-grassv1"}],[{"type":"grass","imageClass":"i-terrain-grassv1"},{"type":"grass","imageClass":"i-terrain-grassv1"},{"type":"grass","imageClass":"i-terrain-grassv1"},{"type":"grass","imageClass":"i-terrain-grassv1"},{"type":"grass","imageClass":"i-terrain-grassv1"},{"type":"grass","imageClass":"i-terrain-grassv1"},{"type":"grass","imageClass":"i-terrain-grassv1"},{"type":"grass","imageClass":"i-terrain-grassv1"},{"type":"grass","imageClass":"i-terrain-grassv1"},{"type":"grass","imageClass":"i-terrain-grassv1"},{"type":"grass","imageClass":"i-terrain-grassv1"},{"type":"grass","imageClass":"i-terrain-grassv1"},{"type":"grass","imageClass":"i-terrain-grassv1"},{"type":"grass","imageClass":"i-terrain-grassv1"},{"type":"grass","imageClass":"i-terrain-grassv1"},{"type":"grass","imageClass":"i-terrain-grassv1"},{"type":"grass","imageClass":"i-terrain-grassv1"},{"type":"grass","imageClass":"i-terrain-grassv1"},{"type":"grass","imageClass":"i-terrain-grassv1"},{"type":"grass","imageClass":"i-terrain-grassv1"},{"type":"grass","imageClass":"i-terrain-grassv1"},{"type":"grass","imageClass":"i-terrain-grassv1"},{"type":"grass","imageClass":"i-terrain-grassv1"},{"type":"grass","imageClass":"i-terrain-grassv1"},{"type":"grass","imageClass":"i-terrain-grassv1"}],[{"type":"grass","imageClass":"i-terrain-grassv1"},{"type":"grass","imageClass":"i-terrain-grassv1"},{"type":"grass","imageClass":"i-terrain-grassv1"},{"type":"grass","imageClass":"i-terrain-grassv1"},{"type":"grass","imageClass":"i-terrain-grassv1"},{"type":"grass","imageClass":"i-terrain-grassv1"},{"type":"grass","imageClass":"i-terrain-grassv1"},{"type":"grass","imageClass":"i-terrain-grassv1"},{"type":"grass","imageClass":"i-terrain-grassv1"},{"type":"grass","imageClass":"i-terrain-grassv1"},{"type":"grass","imageClass":"i-terrain-grassv1"},{"type":"grass","imageClass":"i-terrain-grassv1"},{"type":"grass","imageClass":"i-terrain-grassv1"},{"type":"grass","imageClass":"i-terrain-grassv1"},{"type":"grass","imageClass":"i-terrain-grassv1"},{"type":"grass","imageClass":"i-terrain-grassv1"},{"type":"grass","imageClass":"i-terrain-grassv1"},{"type":"grass","imageClass":"i-terrain-grassv1"},{"type":"grass","imageClass":"i-terrain-grassv1"},{"type":"grass","imageClass":"i-terrain-grassv1"},{"type":"grass","imageClass":"i-terrain-grassv1"},{"type":"grass","imageClass":"i-terrain-grassv1"},{"type":"grass","imageClass":"i-terrain-grassv1"},{"type":"grass","imageClass":"i-terrain-grassv1"},{"type":"grass","imageClass":"i-terrain-grassv1"}],[{"type":"grass","imageClass":"i-terrain-grassv1"},{"type":"grass","imageClass":"i-terrain-grassv1"},{"type":"grass","imageClass":"i-terrain-grassv1"},{"type":"grass","imageClass":"i-terrain-grassv1"},{"type":"grass","imageClass":"i-terrain-grassv1"},{"type":"grass","imageClass":"i-terrain-grassv1"},{"type":"grass","imageClass":"i-terrain-grassv1"},{"type":"grass","imageClass":"i-terrain-grassv1"},{"type":"grass","imageClass":"i-terrain-grassv1"},{"type":"grass","imageClass":"i-terrain-grassv1"},{"type":"grass","imageClass":"i-terrain-grassv1"},{"type":"grass","imageClass":"i-terrain-grassv1"},{"type":"grass","imageClass":"i-terrain-grassv1"},{"type":"grass","imageClass":"i-terrain-grassv1"},{"type":"grass","imageClass":"i-terrain-grassv1"},{"type":"grass","imageClass":"i-terrain-grassv1"},{"type":"grass","imageClass":"i-terrain-grassv1"},{"type":"grass","imageClass":"i-terrain-grassv1"},{"type":"grass","imageClass":"i-terrain-grassv1"},{"type":"grass","imageClass":"i-terrain-grassv1"},{"type":"grass","imageClass":"i-terrain-grassv1"},{"type":"grass","imageClass":"i-terrain-grassv1"},{"type":"grass","imageClass":"i-terrain-grassv1"},{"type":"grass","imageClass":"i-terrain-grassv1"},{"type":"grass","imageClass":"i-terrain-grassv1"}],[{"type":"grass","imageClass":"i-terrain-grassv1"},{"type":"grass","imageClass":"i-terrain-grassv1"},{"type":"grass","imageClass":"i-terrain-grassv1"},{"type":"grass","imageClass":"i-terrain-grassv1"},{"type":"grass","imageClass":"i-terrain-grassv1"},{"type":"grass","imageClass":"i-terrain-grassv1"},{"type":"grass","imageClass":"i-terrain-grassv1"},{"type":"grass","imageClass":"i-terrain-grassv1"},{"type":"grass","imageClass":"i-terrain-grassv1"},{"type":"grass","imageClass":"i-terrain-grassv1"},{"type":"grass","imageClass":"i-terrain-grassv1"},{"type":"grass","imageClass":"i-terrain-grassv1"},{"type":"grass","imageClass":"i-terrain-grassv1"},{"type":"grass","imageClass":"i-terrain-grassv1"},{"type":"grass","imageClass":"i-terrain-grassv1"},{"type":"grass","imageClass":"i-terrain-grassv1"},{"type":"grass","imageClass":"i-terrain-grassv1"},{"type":"grass","imageClass":"i-terrain-grassv1"},{"type":"grass","imageClass":"i-terrain-grassv1"},{"type":"grass","imageClass":"i-terrain-grassv1"},{"type":"grass","imageClass":"i-terrain-grassv1"},{"type":"grass","imageClass":"i-terrain-grassv1"},{"type":"grass","imageClass":"i-terrain-grassv1"},{"type":"grass","imageClass":"i-terrain-grassv1"},{"type":"grass","imageClass":"i-terrain-grassv1"}],[{"type":"grass","imageClass":"i-terrain-grassv1"},{"type":"grass","imageClass":"i-terrain-grassv1"},{"type":"grass","imageClass":"i-terrain-grassv1"},{"type":"grass","imageClass":"i-terrain-grassv1"},{"type":"grass","imageClass":"i-terrain-grassv1"},{"type":"grass","imageClass":"i-terrain-grassv1"},{"type":"grass","imageClass":"i-terrain-grassv1"},{"type":"grass","imageClass":"i-terrain-grassv1"},{"type":"grass","imageClass":"i-terrain-grassv1"},{"type":"grass","imageClass":"i-terrain-grassv1"},{"type":"grass","imageClass":"i-terrain-grassv1"},{"type":"grass","imageClass":"i-terrain-grassv1"},{"type":"grass","imageClass":"i-terrain-grassv1"},{"type":"grass","imageClass":"i-terrain-grassv1"},{"type":"grass","imageClass":"i-terrain-grassv1"},{"type":"grass","imageClass":"i-terrain-grassv1"},{"type":"grass","imageClass":"i-terrain-grassv1"},{"type":"grass","imageClass":"i-terrain-grassv1"},{"type":"grass","imageClass":"i-terrain-grassv1"},{"type":"grass","imageClass":"i-terrain-grassv1"},{"type":"grass","imageClass":"i-terrain-grassv1"},{"type":"grass","imageClass":"i-terrain-grassv1"},{"type":"grass","imageClass":"i-terrain-grassv1"},{"type":"grass","imageClass":"i-terrain-grassv1"},{"type":"grass","imageClass":"i-terrain-grassv1"}],[{"type":"grass","imageClass":"i-terrain-grassv1"},{"type":"grass","imageClass":"i-terrain-grassv1"},{"type":"grass","imageClass":"i-terrain-grassv1"},{"type":"grass","imageClass":"i-terrain-grassv1"},{"type":"grass","imageClass":"i-terrain-grassv1"},{"type":"grass","imageClass":"i-terrain-grassv1"},{"type":"grass","imageClass":"i-terrain-grassv1"},{"type":"grass","imageClass":"i-terrain-grassv1"},{"type":"grass","imageClass":"i-terrain-grassv1"},{"type":"grass","imageClass":"i-terrain-grassv1"},{"type":"grass","imageClass":"i-terrain-grassv1"},{"type":"grass","imageClass":"i-terrain-grassv1"},{"type":"grass","imageClass":"i-terrain-grassv1"},{"type":"grass","imageClass":"i-terrain-grassv1"},{"type":"grass","imageClass":"i-terrain-grassv1"},{"type":"grass","imageClass":"i-terrain-grassv1"},{"type":"grass","imageClass":"i-terrain-grassv1"},{"type":"grass","imageClass":"i-terrain-grassv1"},{"type":"grass","imageClass":"i-terrain-grassv1"},{"type":"grass","imageClass":"i-terrain-grassv1"},{"type":"grass","imageClass":"i-terrain-grassv1"},{"type":"grass","imageClass":"i-terrain-grassv1"},{"type":"grass","imageClass":"i-terrain-grassv1"},{"type":"grass","imageClass":"i-terrain-grassv1"},{"type":"grass","imageClass":"i-terrain-grassv1"}],[{"type":"grass","imageClass":"i-terrain-grassv1"},{"type":"grass","imageClass":"i-terrain-grassv1"},{"type":"grass","imageClass":"i-terrain-grassv1"},{"type":"grass","imageClass":"i-terrain-grassv1"},{"type":"grass","imageClass":"i-terrain-grassv1"},{"type":"grass","imageClass":"i-terrain-grassv1"},{"type":"grass","imageClass":"i-terrain-grassv1"},{"type":"grass","imageClass":"i-terrain-grassv1"},{"type":"grass","imageClass":"i-terrain-grassv1"},{"type":"grass","imageClass":"i-terrain-grassv1"},{"type":"grass","imageClass":"i-terrain-grassv1"},{"type":"grass","imageClass":"i-terrain-grassv1"},{"type":"grass","imageClass":"i-terrain-grassv1"},{"type":"grass","imageClass":"i-terrain-grassv1"},{"type":"grass","imageClass":"i-terrain-grassv1"},{"type":"grass","imageClass":"i-terrain-grassv1"},{"type":"grass","imageClass":"i-terrain-grassv1"},{"type":"grass","imageClass":"i-terrain-grassv1"},{"type":"grass","imageClass":"i-terrain-grassv1"},{"type":"grass","imageClass":"i-terrain-grassv1"},{"type":"grass","imageClass":"i-terrain-grassv1"},{"type":"grass","imageClass":"i-terrain-grassv1"},{"type":"grass","imageClass":"i-terrain-grassv1"},{"type":"grass","imageClass":"i-terrain-grassv1"},{"type":"grass","imageClass":"i-terrain-grassv1"}],[{"type":"grass","imageClass":"i-terrain-grassv1"},{"type":"grass","imageClass":"i-terrain-grassv1"},{"type":"grass","imageClass":"i-terrain-grassv1"},{"type":"grass","imageClass":"i-terrain-grassv1"},{"type":"grass","imageClass":"i-terrain-grassv1"},{"type":"grass","imageClass":"i-terrain-grassv1"},{"type":"grass","imageClass":"i-terrain-grassv1"},{"type":"grass","imageClass":"i-terrain-grassv1"},{"type":"grass","imageClass":"i-terrain-grassv1"},{"type":"grass","imageClass":"i-terrain-grassv1"},{"type":"grass","imageClass":"i-terrain-grassv1"},{"type":"grass","imageClass":"i-terrain-grassv1"},{"type":"grass","imageClass":"i-terrain-grassv1"},{"type":"grass","imageClass":"i-terrain-grassv1"},{"type":"grass","imageClass":"i-terrain-grassv1"},{"type":"grass","imageClass":"i-terrain-grassv1"},{"type":"grass","imageClass":"i-terrain-grassv1"},{"type":"grass","imageClass":"i-terrain-grassv1"},{"type":"grass","imageClass":"i-terrain-grassv1"},{"type":"grass","imageClass":"i-terrain-grassv1"},{"type":"grass","imageClass":"i-terrain-grassv1"},{"type":"grass","imageClass":"i-terrain-grassv1"},{"type":"grass","imageClass":"i-terrain-grassv1"},{"type":"grass","imageClass":"i-terrain-grassv1"},{"type":"grass","imageClass":"i-terrain-grassv1"}],[{"type":"grass","imageClass":"i-terrain-grassv1"},{"type":"grass","imageClass":"i-terrain-grassv1"},{"type":"grass","imageClass":"i-terrain-grassv1"},{"type":"grass","imageClass":"i-terrain-grassv1"},{"type":"grass","imageClass":"i-terrain-grassv1"},{"type":"grass","imageClass":"i-terrain-grassv1"},{"type":"grass","imageClass":"i-terrain-grassv1"},{"type":"grass","imageClass":"i-terrain-grassv1"},{"type":"grass","imageClass":"i-terrain-grassv1"},{"type":"grass","imageClass":"i-terrain-grassv1"},{"type":"grass","imageClass":"i-terrain-grassv1"},{"type":"grass","imageClass":"i-terrain-grassv1"},{"type":"grass","imageClass":"i-terrain-grassv1"},{"type":"grass","imageClass":"i-terrain-grassv1"},{"type":"grass","imageClass":"i-terrain-grassv1"},{"type":"grass","imageClass":"i-terrain-grassv1"},{"type":"grass","imageClass":"i-terrain-grassv1"},{"type":"grass","imageClass":"i-terrain-grassv1"},{"type":"grass","imageClass":"i-terrain-grassv1"},{"type":"grass","imageClass":"i-terrain-grassv1"},{"type":"grass","imageClass":"i-terrain-grassv1"},{"type":"grass","imageClass":"i-terrain-grassv1"},{"type":"grass","imageClass":"i-terrain-grassv1"},{"type":"grass","imageClass":"i-terrain-grassv1"},{"type":"grass","imageClass":"i-terrain-grassv1"}],[{"type":"grass","imageClass":"i-terrain-grassv1"},{"type":"grass","imageClass":"i-terrain-grassv1"},{"type":"grass","imageClass":"i-terrain-grassv1"},{"type":"grass","imageClass":"i-terrain-grassv1"},{"type":"grass","imageClass":"i-terrain-grassv1"},{"type":"grass","imageClass":"i-terrain-grassv1"},{"type":"grass","imageClass":"i-terrain-grassv1"},{"type":"grass","imageClass":"i-terrain-grassv1"},{"type":"grass","imageClass":"i-terrain-grassv1"},{"type":"grass","imageClass":"i-terrain-grassv1"},{"type":"grass","imageClass":"i-terrain-grassv1"},{"type":"grass","imageClass":"i-terrain-grassv1"},{"type":"grass","imageClass":"i-terrain-grassv1"},{"type":"grass","imageClass":"i-terrain-grassv1"},{"type":"grass","imageClass":"i-terrain-grassv1"},{"type":"grass","imageClass":"i-terrain-grassv1"},{"type":"grass","imageClass":"i-terrain-grassv1"},{"type":"grass","imageClass":"i-terrain-grassv1"},{"type":"grass","imageClass":"i-terrain-grassv1"},{"type":"grass","imageClass":"i-terrain-grassv1"},{"type":"grass","imageClass":"i-terrain-grassv1"},{"type":"grass","imageClass":"i-terrain-grassv1"},{"type":"grass","imageClass":"i-terrain-grassv1"},{"type":"grass","imageClass":"i-terrain-grassv1"},{"type":"grass","imageClass":"i-terrain-grassv1"}],[{"type":"grass","imageClass":"i-terrain-grassv1"},{"type":"grass","imageClass":"i-terrain-grassv1"},{"type":"grass","imageClass":"i-terrain-grassv1"},{"type":"grass","imageClass":"i-terrain-grassv1"},{"type":"grass","imageClass":"i-terrain-grassv1"},{"type":"grass","imageClass":"i-terrain-grassv1"},{"type":"grass","imageClass":"i-terrain-grassv1"},{"type":"grass","imageClass":"i-terrain-grassv1"},{"type":"grass","imageClass":"i-terrain-grassv1"},{"type":"grass","imageClass":"i-terrain-grassv1"},{"type":"grass","imageClass":"i-terrain-grassv1"},{"type":"grass","imageClass":"i-terrain-grassv1"},{"type":"grass","imageClass":"i-terrain-grassv1"},{"type":"grass","imageClass":"i-terrain-grassv1"},{"type":"grass","imageClass":"i-terrain-grassv1"},{"type":"grass","imageClass":"i-terrain-grassv1"},{"type":"grass","imageClass":"i-terrain-grassv1"},{"type":"grass","imageClass":"i-terrain-grassv1"},{"type":"grass","imageClass":"i-terrain-grassv1"},{"type":"grass","imageClass":"i-terrain-grassv1"},{"type":"grass","imageClass":"i-terrain-grassv1"},{"type":"grass","imageClass":"i-terrain-grassv1"},{"type":"grass","imageClass":"i-terrain-grassv1"},{"type":"grass","imageClass":"i-terrain-grassv1"},{"type":"grass","imageClass":"i-terrain-grassv1"}],[{"type":"grass","imageClass":"i-terrain-grassv1"},{"type":"grass","imageClass":"i-terrain-grassv1"},{"type":"grass","imageClass":"i-terrain-grassv1"},{"type":"grass","imageClass":"i-terrain-grassv1"},{"type":"grass","imageClass":"i-terrain-grassv1"},{"type":"grass","imageClass":"i-terrain-grassv1"},{"type":"grass","imageClass":"i-terrain-grassv1"},{"type":"grass","imageClass":"i-terrain-grassv1"},{"type":"grass","imageClass":"i-terrain-grassv1"},{"type":"grass","imageClass":"i-terrain-grassv1"},{"type":"grass","imageClass":"i-terrain-grassv1"},{"type":"grass","imageClass":"i-terrain-grassv1"},{"type":"grass","imageClass":"i-terrain-grassv1"},{"type":"grass","imageClass":"i-terrain-grassv1"},{"type":"grass","imageClass":"i-terrain-grassv1"},{"type":"grass","imageClass":"i-terrain-grassv1"},{"type":"grass","imageClass":"i-terrain-grassv1"},{"type":"grass","imageClass":"i-terrain-grassv1"},{"type":"grass","imageClass":"i-terrain-grassv1"},{"type":"grass","imageClass":"i-terrain-grassv1"},{"type":"grass","imageClass":"i-terrain-grassv1"},{"type":"grass","imageClass":"i-terrain-grassv1"},{"type":"grass","imageClass":"i-terrain-grassv1"},{"type":"grass","imageClass":"i-terrain-grassv1"},{"type":"grass","imageClass":"i-terrain-grassv1"}],[{"type":"grass","imageClass":"i-terrain-grassv1"},{"type":"grass","imageClass":"i-terrain-grassv1"},{"type":"grass","imageClass":"i-terrain-grassv1"},{"type":"grass","imageClass":"i-terrain-grassv1"},{"type":"grass","imageClass":"i-terrain-grassv1"},{"type":"grass","imageClass":"i-terrain-grassv1"},{"type":"grass","imageClass":"i-terrain-grassv1"},{"type":"grass","imageClass":"i-terrain-grassv1"},{"type":"grass","imageClass":"i-terrain-grassv1"},{"type":"grass","imageClass":"i-terrain-grassv1"},{"type":"grass","imageClass":"i-terrain-grassv1"},{"type":"grass","imageClass":"i-terrain-grassv1"},{"type":"grass","imageClass":"i-terrain-grassv1"},{"type":"grass","imageClass":"i-terrain-grassv1"},{"type":"grass","imageClass":"i-terrain-grassv1"},{"type":"grass","imageClass":"i-terrain-grassv1"},{"type":"grass","imageClass":"i-terrain-grassv1"},{"type":"grass","imageClass":"i-terrain-grassv1"},{"type":"grass","imageClass":"i-terrain-grassv1"},{"type":"grass","imageClass":"i-terrain-grassv1"},{"type":"grass","imageClass":"i-terrain-grassv1"},{"type":"grass","imageClass":"i-terrain-grassv1"},{"type":"grass","imageClass":"i-terrain-grassv1"},{"type":"grass","imageClass":"i-terrain-grassv1"},{"type":"grass","imageClass":"i-terrain-grassv1"}],[{"type":"grass","imageClass":"i-terrain-grassv1"},{"type":"grass","imageClass":"i-terrain-grassv1"},{"type":"grass","imageClass":"i-terrain-grassv1"},{"type":"grass","imageClass":"i-terrain-grassv1"},{"type":"grass","imageClass":"i-terrain-grassv1"},{"type":"grass","imageClass":"i-terrain-grassv1"},{"type":"grass","imageClass":"i-terrain-grassv1"},{"type":"grass","imageClass":"i-terrain-grassv1"},{"type":"grass","imageClass":"i-terrain-grassv1"},{"type":"grass","imageClass":"i-terrain-grassv1"},{"type":"grass","imageClass":"i-terrain-grassv1"},{"type":"grass","imageClass":"i-terrain-grassv1"},{"type":"grass","imageClass":"i-terrain-grassv1"},{"type":"grass","imageClass":"i-terrain-grassv1"},{"type":"grass","imageClass":"i-terrain-grassv1"},{"type":"grass","imageClass":"i-terrain-grassv1"},{"type":"grass","imageClass":"i-terrain-grassv1"},{"type":"grass","imageClass":"i-terrain-grassv1"},{"type":"grass","imageClass":"i-terrain-grassv1"},{"type":"grass","imageClass":"i-terrain-grassv1"},{"type":"grass","imageClass":"i-terrain-grassv1"},{"type":"grass","imageClass":"i-terrain-grassv1"},{"type":"grass","imageClass":"i-terrain-grassv1"},{"type":"grass","imageClass":"i-terrain-grassv1"},{"type":"grass","imageClass":"i-terrain-grassv1"}],[{"type":"grass","imageClass":"i-terrain-grassv1"},{"type":"grass","imageClass":"i-terrain-grassv1"},{"type":"grass","imageClass":"i-terrain-grassv1"},{"type":"grass","imageClass":"i-terrain-grassv1"},{"type":"grass","imageClass":"i-terrain-grassv1"},{"type":"grass","imageClass":"i-terrain-grassv1"},{"type":"grass","imageClass":"i-terrain-grassv1"},{"type":"grass","imageClass":"i-terrain-grassv1"},{"type":"grass","imageClass":"i-terrain-grassv1"},{"type":"grass","imageClass":"i-terrain-grassv1"},{"type":"grass","imageClass":"i-terrain-grassv1"},{"type":"grass","imageClass":"i-terrain-grassv1"},{"type":"grass","imageClass":"i-terrain-grassv1"},{"type":"grass","imageClass":"i-terrain-grassv1"},{"type":"grass","imageClass":"i-terrain-grassv1"},{"type":"grass","imageClass":"i-terrain-grassv1"},{"type":"grass","imageClass":"i-terrain-grassv1"},{"type":"grass","imageClass":"i-terrain-grassv1"},{"type":"grass","imageClass":"i-terrain-grassv1"},{"type":"grass","imageClass":"i-terrain-grassv1"},{"type":"grass","imageClass":"i-terrain-grassv1"},{"type":"grass","imageClass":"i-terrain-grassv1"},{"type":"grass","imageClass":"i-terrain-grassv1"},{"type":"grass","imageClass":"i-terrain-grassv1"},{"type":"grass","imageClass":"i-terrain-grassv1"}]]},"obstacles":[{"type":"mat","location":{"x":12,"y":0},"data":{"name":"west-jap-plains","x":11,"y":78}},{"type":"mat","location":{"x":11,"y":0},"data":{"name":"west-jap-plains","x":11,"y":78}},{"type":"mat","location":{"x":24,"y":11},"data":{"name":"south-jap-plains","x":1,"y":12}},{"type":"mat","location":{"x":24,"y":10},"data":{"name":"south-jap-plains","x":1,"y":12}}],"buildings":[],"ai":[],"npcs":[]}
